failsafe/__init__.py
failsafe-1.0.4.dist-info/licenses/LICENSE
failsafe-1.0.4.dist-info/METADATA
failsafe-1.0.4.dist-info/WHEEL
failsafe-1.0.4.dist-info/top_level.txt
failsafe-1.0.4.dist-info/RECORD
