Metadata-Version: 2.4
Name: failsafe
Version: 1.0.4
Summary: A lightweight, simpler, more pythonic testing framework
Home-page: https://github.com/TheOmniOnic/failsafe
Author: TheOmniOnic
License: MIT
Classifier: Operating System :: OS Independent
Classifier: License :: OSI Approved :: MIT License
Classifier: Programming Language :: Python :: 3
License-File: LICENSE
Dynamic: author
Dynamic: classifier
Dynamic: description
Dynamic: description-content-type
Dynamic: home-page
Dynamic: license
Dynamic: license-file
Dynamic: summary
